asynchronous/__init__.py
asynchronous/async_class.py
asynchronous/error_class.py
asynchronous/utils.py
pyasync-0.0.2.dist-info/METADATA
pyasync-0.0.2.dist-info/WHEEL
pyasync-0.0.2.dist-info/top_level.txt
pyasync-0.0.2.dist-info/RECORD
