Metadata-Version: 2.1
Name: pyasync
Version: 0.0.2
Summary: Network async tool
Home-page: https://github.com/CG0047/pyasync
Author: weirdofeng
Author-email: weirdofeng@gmail.com
License: UNKNOWN
Project-URL: Bug Tracker, https://github.com/CG0047/pyasync/issues
Platform: UNKNOWN
Classifier: Programming Language :: Python :: 3
Classifier: Programming Language :: Python :: 3.6
Classifier: License :: OSI Approved :: BSD License
Classifier: Operating System :: OS Independent
Requires-Python: >=3.6
Requires-Dist: gevent (==1.4.0)
